AUTHORS.rst
HISTORY.md
README.md
pdfmate/__init__.py
pdfmate/api_async.py
pdfmate/api_sync.py
pdfmate/configuration.py
pdfmate/errors.py
pdfmate/pdfmate.py
pdfmate/source.py
pdfmate/utils.py
pdfmate-0.4.9.dist-info/entry_points.txt
pdfmate-0.4.9.dist-info/LICENSE
pdfmate-0.4.9.dist-info/WHEEL
pdfmate-0.4.9.dist-info/METADATA
pdfmate-0.4.9.dist-info/RECORD
